intspan/__init__.py
intspan/core.py
intspan-1.6.1.dist-info/LICENSE.txt
intspan-1.6.1.dist-info/METADATA
intspan-1.6.1.dist-info/WHEEL
intspan-1.6.1.dist-info/top_level.txt
intspan-1.6.1.dist-info/RECORD
