Metadata-Version: 1.1
Name: intspan
Version: 1.6.1
Summary: Sets of integers like 1,3-7,33
Home-page: https://bitbucket.org/jeunice/intspan
Author: Jonathan Eunice
Author-email: jonathan.eunice@gmail.com
License: Apache License 2.0
Project-URL: Documentation, https://intspan.readthedocs.io/en/latest/
Project-URL: Source, https://bitbucket.org/jeunice/intspan
Project-URL: The Author, https://jonathaneunice.github.io
Keywords: integer set span range intspan intrange intspanlist
Platform: UNKNOWN
Classifier: Development Status :: 5 - Production/Stable
Classifier: Operating System :: OS Independent
Classifier: License :: OSI Approved :: Apache Software License
Classifier: Intended Audience :: Developers
Classifier: Programming Language :: Python
Classifier: Programming Language :: Python :: 2
Classifier: Programming Language :: Python :: 2.7
Classifier: Programming Language :: Python :: 3
Classifier: Programming Language :: Python :: 3.5
Classifier: Programming Language :: Python :: 3.6
Classifier: Programming Language :: Python :: 3.7
Classifier: Programming Language :: Python :: 3.8
Classifier: Programming Language :: Python :: Implementation :: CPython
Classifier: Programming Language :: Python :: Implementation :: PyPy
Classifier: Topic :: Software Development :: Libraries :: Python Modules
